unidiff/__init__.py
unidiff/constants.py
unidiff/errors.py
unidiff/patch.py
unidiff2-0.7.6.dist-info/licenses/AUTHORS
unidiff2-0.7.6.dist-info/licenses/LICENSE
unidiff2-0.7.6.dist-info/METADATA
unidiff2-0.7.6.dist-info/WHEEL
unidiff2-0.7.6.dist-info/entry_points.txt
unidiff2-0.7.6.dist-info/top_level.txt
unidiff2-0.7.6.dist-info/RECORD
