Metadata-Version: 2.4
Name: unidiff2
Version: 0.7.6
Summary: Unified diff parsing/metadata extraction library.
Author-email: Matias Bordese <mbordese@gmail.com>
Maintainer-email: Jef Roelandt <roelandt.jef@plaws.fr>
License: MIT
Project-URL: Homepage, https://github.com/matiasb/python-unidiff
Keywords: unified,diff,parse,metadata
Classifier: Intended Audience :: Developers
Classifier: Development Status :: 4 - Beta
Classifier: Programming Language :: Python :: 3.7
Classifier: Programming Language :: Python :: 3.8
Classifier: Programming Language :: Python :: 3.9
Classifier: Programming Language :: Python :: 3.10
Classifier: Programming Language :: Python :: 3.11
Classifier: License :: OSI Approved :: MIT License
Classifier: Operating System :: OS Independent
Requires-Python: >=3.7
License-File: LICENSE
License-File: AUTHORS
Dynamic: license-file
